pass_gen/__init__.py
pass_gen/main.py
password_generator_cli-0.1.dist-info/METADATA
password_generator_cli-0.1.dist-info/WHEEL
password_generator_cli-0.1.dist-info/entry_points.txt
password_generator_cli-0.1.dist-info/top_level.txt
password_generator_cli-0.1.dist-info/RECORD
