Metadata-Version: 2.1
Name: password-generator-cli
Version: 0.1
Summary: A command-line tool for generating secure passwords.
Home-page: https://github.com/Mahery19/Password_Generator
Author: Mahery
Author-email: maherytsarovana@gmail.com
Classifier: Programming Language :: Python :: 3
Classifier: License :: OSI Approved :: MIT License
Classifier: Operating System :: OS Independent
Requires-Python: >=3.6
Requires-Dist: pyperclip
